correios/__init__.py
correios/main.py
correios/entities/__init__.py
correios/entities/destino.py
correios/entities/endereco.py
correios/entities/evento.py
correios/entities/objeto.py
correios/entities/oec.py
correios/entities/unidade.py
Rastreio_Correios-0.1.4.dist-info/LICENSE
Rastreio_Correios-0.1.4.dist-info/METADATA
Rastreio_Correios-0.1.4.dist-info/WHEEL
Rastreio_Correios-0.1.4.dist-info/top_level.txt
Rastreio_Correios-0.1.4.dist-info/RECORD
