Metadata-Version: 2.1
Name: Rastreio-Correios
Version: 0.1.4
Summary: Rastreamento de pacotes do correio
Home-page: https://github.com/rennancockles/rastreio-correios
Author: Rennan Cockles
Author-email: rcdev@hotmail.com.br
License: MIT
Project-URL: Source Code, https://github.com/rennancockles/rastreio-correios
Project-URL: Documentation, https://rastreio-correios.r3ck.com.br
Keywords: correios,ect,rastreio,rastreamento,track
Platform: UNKNOWN
Classifier: Operating System :: OS Independent
Classifier: Programming Language :: Python :: 3
Classifier: Programming Language :: Python
Classifier: Topic :: Software Development :: Libraries :: Python Modules
Classifier: Topic :: Software Development :: Libraries
Classifier: Topic :: Software Development
Classifier: Typing :: Typed
Classifier: Development Status :: 4 - Beta
Classifier: Intended Audience :: Developers
Classifier: License :: OSI Approved :: MIT License
Classifier: Programming Language :: Python :: 3 :: Only
Classifier: Programming Language :: Python :: 3.8
Classifier: Programming Language :: Python :: 3.9
Requires-Python: >=3.8
Requires-Dist: fastapi
Requires-Dist: requests
Requires-Dist: pydantic
